CHANGELOG.txt
LICENSE.txt
MANIFEST.in
README.txt
setup.py
ANbasicCalculator/__init__.py
ANbasicCalculator.egg-info/PKG-INFO
ANbasicCalculator.egg-info/SOURCES.txt
ANbasicCalculator.egg-info/dependency_links.txt
ANbasicCalculator.egg-info/top_level.txt