Metadata-Version: 1.1
Name: ANbasicCalculator
Version: 0.0.1
Summary: A very basic calutor.
Home-page: UNKNOWN
Author: Ayan
Author-email: ayanU881@gmail.com
License: MIT
Keywords: python,calculator
Platform: UNKNOWN
Classifier: Development Status :: 5 - Production/Stable
Classifier: Intended Audience :: Education
Classifier: Programming Language :: Python :: 3
Classifier: Operating System :: Microsoft :: Windows :: Windows 10
Classifier: License :: OSI Approved :: MIT License
